libpng/__init__.py
libpng/ld-musl-x86_64.so.1
libpng/libc.musl-x86_64.so.1
libpng/libpng.la
libpng/libpng.so
libpng/libpng16.la
libpng/libpng16.so
libpng/libpng16.so.16
libpng/libpng16.so.16.38.0
libpng/libz.so
libpng/libz.so.1
libpng/libz.so.1.2.11
libpng_bins-0.0.3.dist-info/METADATA
libpng_bins-0.0.3.dist-info/RECORD
libpng_bins-0.0.3.dist-info/WHEEL
libpng_bins-0.0.3.dist-info/top_level.txt
