Metadata-Version: 2.1
Name: libpng-bins
Version: 0.0.3
Summary: Libraries for LibPNG on Alpine Linux
Home-page: https://github.com/spencer-hanson/libpng
Author: Spencer Hanson
Author-email: UNKNOWN
License: UNKNOWN
Keywords: libpng
Platform: UNKNOWN
